ray_proxy/__init__.py
ray_proxy/async_interpreter.py
ray_proxy/cluster_resource.py
ray_proxy/cluster_task_scheduler.py
ray_proxy/injected_resource.py
ray_proxy/interface.py
ray_proxy/local_var.py
ray_proxy/prepared.py
ray_proxy/py_environment.py
ray_proxy/ray_queue.py
ray_proxy/releasable.py
ray_proxy/remote_env.py
ray_proxy/remote_prog_bar.py
ray_proxy/remote_proxy.py
ray_proxy/resource_design.py
ray_proxy/resource_scheduler.py
ray_proxy/resource_scheduler_client.py
ray_proxy/serialization_check.py
ray_proxy/type_aliases.py
ray_proxy/util.py
ray_proxy/var_interface.py
ray_proxy-0.1.13.dist-info/LICENSE
ray_proxy-0.1.13.dist-info/METADATA
ray_proxy-0.1.13.dist-info/WHEEL
ray_proxy-0.1.13.dist-info/RECORD
